MANIFEST.in
setup.py
django_rest_raml.egg-info/PKG-INFO
django_rest_raml.egg-info/SOURCES.txt
django_rest_raml.egg-info/dependency_links.txt
django_rest_raml.egg-info/top_level.txt
rest_framework_raml/__init__.py
rest_framework_raml/renderers.py
rest_framework_raml/static/rest_framework_raml/favicon.ico
rest_framework_raml/static/rest_framework_raml/authentication/oauth1.html
rest_framework_raml/static/rest_framework_raml/authentication/oauth2.html
rest_framework_raml/static/rest_framework_raml/fonts/Lato-Black.woff2
rest_framework_raml/static/rest_framework_raml/fonts/Lato-Black2.woff2
rest_framework_raml/static/rest_framework_raml/fonts/Lato-BlackItalic.woff2
rest_framework_raml/static/rest_framework_raml/fonts/Lato-BlackItalic2.woff2
rest_framework_raml/static/rest_framework_raml/fonts/Lato-Blak.woff2
rest_framework_raml/static/rest_framework_raml/fonts/Lato-Blak2.woff2
rest_framework_raml/static/rest_framework_raml/fonts/Lato-Bold.woff2
rest_framework_raml/static/rest_framework_raml/fonts/Lato-Bold2.woff2
rest_framework_raml/static/rest_framework_raml/fonts/Lato-BoldItalic.woff2
rest_framework_raml/static/rest_framework_raml/fonts/Lato-BoldItalic2.woff2
rest_framework_raml/static/rest_framework_raml/fonts/Lato-Hairline-Italic.woff2
rest_framework_raml/static/rest_framework_raml/fonts/Lato-Hairline-Italic2.woff2
rest_framework_raml/static/rest_framework_raml/fonts/Lato-Hairline.woff2
rest_framework_raml/static/rest_framework_raml/fonts/Lato-Hairline2.woff2
rest_framework_raml/static/rest_framework_raml/fonts/Lato-Italic.woff2
rest_framework_raml/static/rest_framework_raml/fonts/Lato-Italic2.woff2
rest_framework_raml/static/rest_framework_raml/fonts/Lato-Light.woff2
rest_framework_raml/static/rest_framework_raml/fonts/Lato-Light2.woff2
rest_framework_raml/static/rest_framework_raml/fonts/Lato-LightItalic.woff2
rest_framework_raml/static/rest_framework_raml/fonts/Lato-LightItalic2.woff2
rest_framework_raml/static/rest_framework_raml/fonts/Lato-Regular.woff2
rest_framework_raml/static/rest_framework_raml/fonts/Lato-Regular2.woff2
rest_framework_raml/static/rest_framework_raml/fonts/Source-Code-Pro-2.woff2
