Metadata-Version: 1.1
Name: django-rest-raml
Version: 0.0.1
Summary: RAML Documentation Generator for Django REST framework
Home-page: http://github.com/tomchristie/django-rest-raml/
Author: Tom Christie
Author-email: tom@tomchristie.com
License: BSD
Platform: UNKNOWN
Classifier: Intended Audience :: Developers
Classifier: License :: OSI Approved :: BSD License
Classifier: Operating System :: OS Independent
Classifier: Programming Language :: Python
Classifier: Programming Language :: Python :: 3
